devleaps/__init__.py
devleaps/policies/__init__.py
devleaps/policies/client/__init__.py
devleaps/policies/client/client.py
devleaps/policies/client/config.py
devleaps/policies/example/__init__.py
devleaps/policies/example/main.py
devleaps/policies/server/__init__.py
devleaps/policies/server/executor.py
devleaps/policies/server/registry.py
devleaps/policies/server/server.py
devleaps/policies/server/claude_code/__init__.py
devleaps/policies/server/claude_code/mapper.py
devleaps/policies/server/claude_code/routes.py
devleaps/policies/server/claude_code/api/__init__.py
devleaps/policies/server/claude_code/api/enums.py
devleaps/policies/server/claude_code/api/notification.py
devleaps/policies/server/claude_code/api/output_base.py
devleaps/policies/server/claude_code/api/post_tool_use.py
devleaps/policies/server/claude_code/api/pre_compact.py
devleaps/policies/server/claude_code/api/pre_tool_use.py
devleaps/policies/server/claude_code/api/request_wrapper.py
devleaps/policies/server/claude_code/api/session_end.py
devleaps/policies/server/claude_code/api/session_start.py
devleaps/policies/server/claude_code/api/stop.py
devleaps/policies/server/claude_code/api/user_prompt_submit.py
devleaps/policies/server/common/__init__.py
devleaps/policies/server/common/enums.py
devleaps/policies/server/common/models.py
devleaps/policies/server/cursor/__init__.py
devleaps/policies/server/cursor/mapper.py
devleaps/policies/server/cursor/routes.py
devleaps/policies/server/cursor/api/__init__.py
devleaps/policies/server/cursor/api/after_file_edit.py
devleaps/policies/server/cursor/api/before_mcp_execution.py
devleaps/policies/server/cursor/api/before_read_file.py
devleaps/policies/server/cursor/api/before_shell_execution.py
devleaps/policies/server/cursor/api/before_submit_prompt.py
devleaps/policies/server/cursor/api/common.py
devleaps/policies/server/cursor/api/stop.py
devleaps/policies/server/session/__init__.py
devleaps/policies/server/session/state.py
devleaps_agent_policies-1.0.5.dist-info/METADATA
devleaps_agent_policies-1.0.5.dist-info/WHEEL
devleaps_agent_policies-1.0.5.dist-info/entry_points.txt
devleaps_agent_policies-1.0.5.dist-info/licenses/LICENSE
devleaps_agent_policies-1.0.5.dist-info/RECORD
