Metadata-Version: 2.4
Name: devleaps-agent-policies
Version: 1.0.5
Summary: Policy framework for Claude Code and Cursor hooks
Author: DevLeaps
License: MIT
License-File: LICENSE
Keywords: ai,claude-code,cursor,hooks,policies,security
Classifier: Development Status :: 4 - Beta
Classifier: Intended Audience :: Developers
Classifier: License :: OSI Approved :: MIT License
Classifier: Programming Language :: Python :: 3
Classifier: Programming Language :: Python :: 3.9
Classifier: Programming Language :: Python :: 3.10
Classifier: Programming Language :: Python :: 3.11
Classifier: Programming Language :: Python :: 3.12
Classifier: Topic :: Security
Classifier: Topic :: Software Development :: Libraries :: Python Modules
Requires-Python: >=3.9
Requires-Dist: fastapi==0.118.0
Requires-Dist: pydantic==2.12.5
Requires-Dist: requests==2.32.5
Requires-Dist: uvicorn==0.37.0
Provides-Extra: dev
Requires-Dist: httpx==0.28.1; extra == 'dev'
Requires-Dist: pytest==8.4.2; extra == 'dev'
